sv/slave.sv
module slave (
    input [0:0] PCLK,
    input [0:0] PRESET,
    input [0:0] PSEL,
    input [0:0] PENABLE,
    input [0:0] PWRITE,
    input [31:0] PRWADDR,          
    input [31:0] PRWDATA,
    output reg [31:0] PRDATA1,     
    output reg [0:0] PREADY   
);

reg [3:0] state;        // Состояние конечного автомата
reg [31:0] memory [0:127];
reg [2:0] c;

always @(PRESET) begin

if (PRESET == 1'b1) begin
    // Сброс в начальное состояние
    state <= 4'b0000;
    PRDATA1 <= 32'b00000000000000000000000000000000;

    PREADY = 0;
end
end

// Логика конечного автомата
always @(posedge PCLK or posedge PRESET) begin

if (PRESET) begin
    // Сброс в начальное состояние
    state <= 4'b0000;
    PRDATA1 <= 32'b00000000000000000000000000000000;
end else begin    
    if(PSEL == 1'b1 && PENABLE == 1'b0 && PWRITE == 1'b0) begin 
        PREADY = 0; 
    end
        
    else if(PSEL == 1'b1 && PENABLE == 1'b1 && PWRITE == 1'b0) begin  
        PRDATA1 <= memory[PRWADDR];
        PREADY = 1;
        $display("Чтение");
    end

    else if(PSEL == 1'b1 && PENABLE == 1'b0 && PWRITE == 1'b1) begin  
        PREADY = 0; 
    end

    else if(PSEL == 1'b1 && PENABLE == 1'b1 && PWRITE == 1'b1) begin  
        PREADY = 1;
        PRDATA1 <= PRWDATA;
        memory[PRWADDR] <= PRWDATA;
        $display("Запись");
    end

    else begin
        PREADY = 0;
    end

    end
end
endmodule

sv/master.sv
module master (
    input [0:0] PCLK,
    input [0:0] PRESET,

    input [0:0] PSEL,
    input [0:0] PREADY,
    input [0:0] transfer,

    input [0:0] PWRITE,
    input [31:0] PADDR,
    input [31:0] PDATA, 
    output reg [0:0] PENABLE,
    output reg [31:0] PRWDATA,
    output reg [31:0] PRWADDR
);

reg [31:0] memory [0:127];
reg [1:0] state = 2'b00;

task apb_read;
input [31:0] addr;
    begin

        PRWDATA <= PDATA;

        PRWADDR <= addr;
    end
endtask

task apb_write;
input [31:0] addr;
input [31:0] data;
    begin

        PRWDATA <= data;
        PRWADDR <= addr;
    end
endtask

integer i;
reg [31:0] temp;

always @(posedge PCLK or posedge PRESET or posedge PENABLE) begin

    if (PRESET == 1'b1) begin 
        PRWDATA <= 0;
        PRWADDR <= 0;
        state = 2'b00;
    end

    case (state)
    2'b00:
    begin
        PENABLE = 1'b0;
        if (PSEL == 1'b1 && transfer == 1'b1) begin 
            if (PWRITE == 1'b1) begin
                state <= 2'b01;
            end
            else begin
                state <= 2'b10;
            end
        end
    end

    2'b01:
    begin
        PENABLE = 1'b1;
        if (PSEL == 1'b1 && transfer == 1'b1 && PREADY == 1'b1) begin
            apb_write(PADDR,PDATA);
            state <= 2'b11;
        end
    end

    2'b10:
    begin
        PENABLE <= 1'b1;
        if (PSEL == 1'b1 && transfer == 1'b1 && PREADY == 1'b1) begin
            apb_read(PADDR);
            state <= 2'b11;
        end
    end

    2'b11:begin
        if (PSEL == 1'b1 && transfer == 1'b1 && PREADY == 1'b1) begin
            if (PWRITE == 1'b1) begin
                state <= 2'b01;
            end
            else begin
                state <= 2'b10;
            end
        end

        if (PSEL == 1'b1 && transfer == 1'b0 && PREADY == 1'b1) begin
            state <= 2'b00;
        end
    end

    endcase
end
endmodule

testbench.sv
// iverilog -o testbench.vvp testbench.sv 
// vvp testbench.vvp

`include "master.sv"
`include "slave.sv"

module testbench;

reg [0:0] PCLK;
reg [0:0] PRESET;

reg [0:0] PSEL;
reg [0:0] transfer;
reg [0:0] r;
reg [0:0] PWRITE;

reg [31:0] PADDR;
reg [31:0] PDATA;

wire [0:0] PENABLE;
wire [31:0] PRWDATA;
wire [31:0] PRWADDR;

wire [31:0] PRDATA1;
wire [0:0] PREADY;

master m (
    .PCLK(PCLK),
    .PRESET(PRESET),
    .PSEL(PSEL),
    .PREADY(PREADY),
    .transfer(transfer),
    .PWRITE(PWRITE),      
    .PADDR(PADDR),
    .PDATA(PDATA),

    .PENABLE(PENABLE),
    .PRWDATA(PRWDATA),
    .PRWADDR(PRWADDR)
);

slave s (
    .PCLK(PCLK),
    .PRESET(PRESET),
    .PSEL(PSEL),
    .PENABLE(PENABLE),
    .PWRITE(PWRITE),

    .PRWDATA(PRWDATA),  // master out, slave in data
    .PRWADDR(PRWADDR),  // master out, slava in addr

    .PRDATA1(PRDATA1),        // slave out data
    .PREADY(PREADY)        
);

initial begin
    $dumpfile("testbench.vcd");
    $dumpvars(0,testbench);
    PADDR = 32'b00000000000000000000000000000000;
    PDATA = 32'h00000309;

    PWRITE = 1'b1;
    
    PCLK = 1'b0;
    PRESET = 0;
    PSEL = 0;
    transfer = 1'b1;

    PRESET = 1;
    #10;
    PRESET = 0;
    PSEL = 1;
    #30;
    PSEL = 0;
    #20;

    PADDR = 32'b00000000000000000000000000000100;
    PDATA = 32'h28122023;
    PSEL = 1;
    #30;
    PSEL = 0;
    #20;

    PADDR = 32'b00000000000000000000000000001000;
    PDATA = 32'h416c656b;
    PSEL = 1;
    #30;
    PSEL = 0;
    #20;

    PADDR = 32'b000000000000000000000000001100;
    PDATA = 32'h4c656500;
    PSEL = 1;
    #30;
    PSEL = 0;
    #20;

    $finish;
end

always begin
    #5 PCLK = ~PCLK;
end

endmodule

testbench.vcd
$date
	Thu Dec 28 12:29:29 2023
$end
$version
	Icarus Verilog
$end
$timescale
	1s
$end
$scope module testbench $end
$var wire 32 ! PRWDATA [31:0] $end
$var wire 32 " PRWADDR [31:0] $end
$var wire 1 # PREADY $end
$var wire 32 $ PRDATA1 [31:0] $end
$var wire 1 % PENABLE $end
$var reg 32 & PADDR [31:0] $end
$var reg 1 ' PCLK $end
$var reg 32 ( PDATA [31:0] $end
$var reg 1 ) PRESET $end
$var reg 1 * PSEL $end
$var reg 1 + PWRITE $end
$var reg 1 , transfer $end
$scope module m $end
$var wire 32 - PADDR [31:0] $end
$var wire 1 ' PCLK $end
$var wire 32 . PDATA [31:0] $end
$var wire 1 ) PRESET $end
$var wire 1 * PSEL $end
$var wire 1 + PWRITE $end
$var wire 1 , transfer $end
$var wire 1 # PREADY $end
$var reg 1 % PENABLE $end
$var reg 32 / PRWADDR [31:0] $end
$var reg 32 0 PRWDATA [31:0] $end
$var reg 2 1 state [1:0] $end
$scope task apb_read $end
$var reg 32 2 addr [31:0] $end
$upscope $end
$scope task apb_write $end
$var reg 32 3 addr [31:0] $end
$var reg 32 4 data [31:0] $end
$upscope $end
$upscope $end
$scope module s $end
$var wire 1 ' PCLK $end
$var wire 1 % PENABLE $end
$var wire 1 ) PRESET $end
$var wire 32 5 PRWADDR [31:0] $end
$var wire 32 6 PRWDATA [31:0] $end
$var wire 1 * PSEL $end
$var wire 1 + PWRITE $end
$var reg 32 7 PRDATA1 [31:0] $end
$var reg 1 # PREADY $end
$var reg 4 8 state [3:0] $end
$upscope $end
$upscope $end
$enddefinitions $end
#0
$dumpvars
b0 8
b0 7
b0 6
b0 5
bx 4
bx 3
bx 2
b0 1
b0 0
b0 /
b1100001001 .
b0 -
1,
1+
0*
1)
b1100001001 (
0'
b0 &
0%
b0 $
0#
b0 "
b0 !
$end
#5
1'
#10
0'
1*
0)
#15
b1 1
1'
#20
0'
#25
1%
1'
#30
0'
#35
b11 1
b1100001001 !
b1100001001 0
b1100001001 6
b1100001001 4
b0 3
1#
1'
#40
0'
0*
#45
0#
1'
#50
0'
#55
1'
#60
0'
1*
b101000000100100010000000100011 (
b101000000100100010000000100011 .
b100 &
b100 -
#65
b1 1
b1100001001 $
b1100001001 7
1#
1'
#70
0'
#75
b11 1
b100 "
b100 /
b100 5
b101000000100100010000000100011 !
b101000000100100010000000100011 0
b101000000100100010000000100011 6
b101000000100100010000000100011 4
b100 3
1'
#80
0'
#85
b1 1
b101000000100100010000000100011 $
b101000000100100010000000100011 7
1'
#90
0'
0*
#95
0#
1'
#100
0'
#105
1'
#110
0'
1*
b1000001011011000110010101101011 (
b1000001011011000110010101101011 .
b1000 &
b1000 -
#115
b11 1
b1000 "
b1000 /
b1000 5
b1000001011011000110010101101011 !
b1000001011011000110010101101011 0
b1000001011011000110010101101011 6
b1000001011011000110010101101011 4
b1000 3
1#
1'
#120
0'
#125
b1 1
b1000001011011000110010101101011 $
b1000001011011000110010101101011 7
1'
#130
0'
#135
b11 1
1'
#140
0'
0*
#145
0#
1'
#150
0'
#155
1'
#160
0'
1*
b1001100011001010110010100000000 (
b1001100011001010110010100000000 .
b1100 &
b1100 -
#165
b1 1
1#
1'
#170
0'
#175
b11 1
b1100 "
b1100 /
b1100 5
b1001100011001010110010100000000 !
b1001100011001010110010100000000 0
b1001100011001010110010100000000 6
b1001100011001010110010100000000 4
b1100 3
1'
#180
0'
#185
b1 1
b1001100011001010110010100000000 $
b1001100011001010110010100000000 7
1'
#190
0'
0*
#195
0#
1'
